odoo8_addon_project_baseuser-8.0.1.0.0-py2.7-nspkg.pth
odoo_addons/project_baseuser/project_view.xml
odoo_addons/project_baseuser/README.md
odoo_addons/project_baseuser/__openerp__.py
odoo_addons/project_baseuser/project.py
odoo_addons/project_baseuser/__init__.py
odoo_addons/project_baseuser/security/project_security.xml
odoo_addons/project_baseuser/security/ir.model.access.csv
odoo_addons/project_baseuser/i18n/es.po
odoo_addons/project_baseuser/i18n/sl.po
odoo_addons/project_baseuser/i18n/project_baseuser.pot
odoo_addons/project_baseuser/i18n/de.po
odoo8_addon_project_baseuser-8.0.1.0.0.dist-info/top_level.txt
odoo8_addon_project_baseuser-8.0.1.0.0.dist-info/WHEEL
odoo8_addon_project_baseuser-8.0.1.0.0.dist-info/RECORD
odoo8_addon_project_baseuser-8.0.1.0.0.dist-info/metadata.json
odoo8_addon_project_baseuser-8.0.1.0.0.dist-info/DESCRIPTION.rst
odoo8_addon_project_baseuser-8.0.1.0.0.dist-info/METADATA
odoo8_addon_project_baseuser-8.0.1.0.0.dist-info/namespace_packages.txt
