Metadata-Version: 2.0
Name: odoo8-addon-project-baseuser
Version: 8.0.1.0.0
Summary: Extend Project user roles to support more complex use cases
Home-page: UNKNOWN
Author: UNKNOWN
Author-email: UNKNOWN
License: AGPL-3
Platform: UNKNOWN
Requires-Dist: odoo (<9.0a,>=8.0a)
Requires-Dist: odoo8-addon-project-stage-state
Classifier: Programming Language :: Python :: 2.7
Classifier: Framework :: Odoo
Classifier: License :: OSI Approved :: GNU Affero General Public License v3
